.DS_Store
classify/__init__.py
classify/cnn_model.py
classify/predict.py
classify/process_data.py
classify/rnn_model.py
classify/run_cnn.py
classify/run_rnn.py
data/__init__.py
data/cnews_loader.py
helper/__init__.py
helper/cnews_group.py
zhanglei-0.0.6.dist-info/LICENSE
zhanglei-0.0.6.dist-info/METADATA
zhanglei-0.0.6.dist-info/WHEEL
zhanglei-0.0.6.dist-info/top_level.txt
zhanglei-0.0.6.dist-info/RECORD
